sai_akruti/__init__.py
sai_akruti/settings.py
sai_akruti/sources.py
sai_akruti-0.5.5.dist-info/METADATA
sai_akruti-0.5.5.dist-info/WHEEL
sai_akruti-0.5.5.dist-info/RECORD
