Metadata-Version: 2.3
Name: sai-akruti
Version: 0.5.5
Summary: Centralized Settings Loader for Python Apps
License: MIT
Author: Manish Chitnis
Author-email: mnc@sentinelrisk.ai
Requires-Python: >3.10,<4.0
Classifier: License :: OSI Approved :: MIT License
Classifier: Programming Language :: Python :: 3
Classifier: Programming Language :: Python :: 3.11
Classifier: Programming Language :: Python :: 3.12
Classifier: Programming Language :: Python :: 3.13
Requires-Dist: boto3 (>=1.40.15,<2.0.0)
Requires-Dist: pydantic-settings (>=2.0.0,<3.0.0)
